imd_cookie_cutter/__helper.py
imd_cookie_cutter/__init__.py
imd_cookie_cutter/__processor.py
imd_cookie_cutter/__selectors.py
imd_cookie_cutter/__typecaster.py
imd_cookie_cutter/__vectors.py
imd_cookie_cutter-1.0.2.dist-info/LICENSE
imd_cookie_cutter-1.0.2.dist-info/METADATA
imd_cookie_cutter-1.0.2.dist-info/WHEEL
imd_cookie_cutter-1.0.2.dist-info/top_level.txt
imd_cookie_cutter-1.0.2.dist-info/RECORD
