Metadata-Version: 2.1
Name: imd-cookie-cutter
Version: 1.0.2
Summary: A tool for removing atoms in IMD config files, just like a cookie cutter in higher dimensions.
Home-page: https://github.com/bliepp/imd_cookie_cutter
Author: bliepp
License: UNKNOWN
Platform: UNKNOWN
Classifier: Development Status :: 5 - Production/Stable
Classifier: Programming Language :: Python :: 3
Classifier: License :: OSI Approved :: MIT License
Classifier: Operating System :: OS Independent
Requires-Python: >=3.6
